gwas2vcf/__init__.py
gwas2vcf/convert_to_vcf.py
gwas2vcf-0.1.9.dist-info/METADATA
gwas2vcf-0.1.9.dist-info/WHEEL
gwas2vcf-0.1.9.dist-info/entry_points.txt
gwas2vcf-0.1.9.dist-info/top_level.txt
gwas2vcf-0.1.9.dist-info/RECORD
