Metadata-Version: 2.1
Name: gwas2vcf
Version: 0.1.9
Summary: A tool to convert GWAS TSV files to VCF format
Home-page: https://github.com/VJ-Ulaganathan/gwas2vcf/
Author: Pr (France). Dr. rer. nat. Vijay K. ULAGANATHAN
Author-email: vijay-kumar.ulaganathan@uni-tuebingen.de
Classifier: Programming Language :: Python :: 3
Classifier: License :: OSI Approved :: MIT License
Classifier: Operating System :: OS Independent
Requires-Python: >=3.11.6
Requires-Dist: pandas
Requires-Dist: tqdm
